dm_aiomodbus/__init__.py
dm_aiomodbus/aiomodbus_base_client.py
dm_aiomodbus/aiomodbus_serial_client.py
dm_aiomodbus/aiomodbus_tcp_client.py
dm_aiomodbus/types.py
dm_aiomodbus-0.3.9.dist-info/METADATA
dm_aiomodbus-0.3.9.dist-info/WHEEL
dm_aiomodbus-0.3.9.dist-info/top_level.txt
dm_aiomodbus-0.3.9.dist-info/RECORD
