Metadata-Version: 2.4
Name: dm-aiomodbus
Version: 0.3.9
Summary: This is my custom aiomodbus client
Home-page: https://pypi.org/project/dm-aiomodbus
Author: dimka4621
Author-email: mismartconfig@gmail.com
Project-URL: GitHub, https://github.com/MykhLibs/dm-aiomodbus
Keywords: dm aiomodbus
Classifier: Programming Language :: Python :: 3.8
Classifier: License :: OSI Approved :: MIT License
Classifier: Operating System :: OS Independent
Requires-Python: >=3.8
Requires-Dist: dm-logger~=0.6.2
Requires-Dist: pyserial==3.5
Requires-Dist: pymodbus==3.8.6
Dynamic: author
Dynamic: author-email
Dynamic: classifier
Dynamic: description
Dynamic: description-content-type
Dynamic: home-page
Dynamic: keywords
Dynamic: project-url
Dynamic: requires-dist
Dynamic: requires-python
Dynamic: summary
